visionstudio/__init__.py
visionstudio/cli.py
visionstudio/core.py
visionstudio-0.1.0.dist-info/licenses/LICENSE
visionstudio-0.1.0.dist-info/METADATA
visionstudio-0.1.0.dist-info/WHEEL
visionstudio-0.1.0.dist-info/top_level.txt
visionstudio-0.1.0.dist-info/RECORD
