Metadata-Version: 2.4
Name: visionstudio
Version: 0.1.0
Summary: A starter package to build Agents
Home-page: https://github.com/datamarkin/agents
Author: Emrah NAZIF
Author-email: Emrah NAZIF <emrah@datamarkin.com>
License: MIT
Classifier: Programming Language :: Python :: 3
Classifier: License :: OSI Approved :: MIT License
Classifier: Operating System :: OS Independent
Requires-Python: >=3.7
License-File: LICENSE
Dynamic: author
Dynamic: home-page
Dynamic: license-file
Dynamic: requires-python
